{
    "$schema": "https://schema.management.azure.com/schemas/2015-01-01/deploymentParameters.json#",
    "contentVersion": "1.0.0.0",
    "parameters": { 
        "location": {
            "value": "Australia Southeast"
        },
        "environmentName": {
            "value": "delir2env3"
        },
        "projectName": {
            "value": "delir2project3"
        },
        "logicAppName": {
            "value": "delir2la3"
        },
        "appServicePlanName": {
            "value": "delir2asp3"
        },
        "storageName": {
            "value": "delir2storage3"
        },
        "kind": {
            "value": "StorageV2"
        },
        "skuName": {
            "value": "Standard_LRS"
        },
        "skuTier": {
            "value": "Standard"
          }
        }
    }